setup.py
src/dtps_ui/__init__.py
src/dtps_ui/app.py
src/dtps_ui/cli_serve.py
src/dtps_ui/types.py
src/dtps_ui/utils.py
src/dtps_ui.egg-info/PKG-INFO
src/dtps_ui.egg-info/SOURCES.txt
src/dtps_ui.egg-info/dependency_links.txt
src/dtps_ui.egg-info/entry_points.txt
src/dtps_ui.egg-info/requires.txt
src/dtps_ui.egg-info/top_level.txt
src/dtps_ui/assets/cbor.min.js
src/dtps_ui/assets/dtps_ui.js
src/dtps_ui/assets/dtps_ui_include.html
src/dtps_ui/assets/jquery-3.7.1.min.js
src/dtps_ui/assets/js-yaml.min.js